pypret/__init__.py
pypret/autocorrelation.py
pypret/fourier.py
pypret/frequencies.py
pypret/graphics.py
pypret/lib.py
pypret/material.py
pypret/mesh_data.py
pypret/pnps.py
pypret/pulse.py
pypret/pulse_error.py
pypret/random_pulse.py
pypret/io/__init__.py
pypret/io/handlers.py
pypret/io/io.py
pypret/io/options.py
pypret/retrieval/__init__.py
pypret/retrieval/nlo_retriever.py
pypret/retrieval/retriever.py
pypret/retrieval/step_retriever.py
pypret_pymodaq-1.0.0.dist-info/licenses/LICENSE
pypret_pymodaq-1.0.0.dist-info/METADATA
pypret_pymodaq-1.0.0.dist-info/WHEEL
pypret_pymodaq-1.0.0.dist-info/top_level.txt
pypret_pymodaq-1.0.0.dist-info/RECORD
