Metadata-Version: 2.4
Name: pypret_pymodaq
Version: 1.0.0
Summary: fork of Python for Pulse Retrieval for PyMoDAQ
Home-page: https://github.com/PyMoDAQ/pypret_pymodaq
Author: S. J. Weber
Author-email: sebastien.weber@cemes.fr
License: MIT
Classifier: Programming Language :: Python :: 3
Classifier: Development Status :: 5 - Production/Stable
Classifier: Environment :: Other Environment
Classifier: Intended Audience :: Science/Research
Classifier: Topic :: Scientific/Engineering :: Human Machine Interfaces
Classifier: Topic :: Scientific/Engineering :: Visualization
Classifier: License :: OSI Approved :: MIT License
Classifier: Operating System :: OS Independent
Classifier: Topic :: Software Development :: Libraries :: Python Modules
Classifier: Topic :: Software Development :: User Interfaces
Requires-Python: >=3.6
License-File: LICENSE
Requires-Dist: h5py
Requires-Dist: loky
Requires-Dist: scipy
Dynamic: license-file
